{
  "books": [
    {
      "title": "123",
      "authorName": "sdsds",
      "authorSurname": "sdsds",
      "pages": 111,
      "completedPages": "2",
      "completed": true,
      "id": 1
    },
    {
      "title": "123",
      "authorName": "sdsds",
      "authorSurname": "sdsds",
      "pages": 111,
      "completedPages": "2",
      "completed": true,
      "id": 2
    },
    {
      "title": "123",
      "authorName": "sdsds",
      "authorSurname": "sdsds",
      "pages": 111,
      "completedPages": "2",
      "completed": true,
      "id": 3
    },
    {
      "title": "123",
      "authorName": "sdsds",
      "authorSurname": "sdsds",
      "pages": 111,
      "completedPages": "2",
      "completed": true,
      "id": 4
    },
    {
      "title": "123",
      "authorName": "sdsds",
      "authorSurname": "sdsds",
      "pages": 111,
      "completedPages": "2",
      "completed": true,
      "id": 5
    },
    {
      "title": "123",
      "authorName": "sdsds",
      "authorSurname": "sdsds",
      "pages": 111,
      "completedPages": "2",
      "completed": true,
      "id": 6
    },
    {
      "title": "123",
      "authorName": "sdsds",
      "authorSurname": "sdsds",
      "pages": 111,
      "completedPages": "2",
      "completed": true,
      "id": 7
    },
    {
      "title": "123",
      "authorName": "sdsds",
      "authorSurname": "sdsds",
      "pages": 111,
      "completedPages": "2",
      "completed": true,
      "id": 8
    },
    {
      "title": "123",
      "authorName": "sdsds",
      "authorSurname": "sdsds",
      "pages": 111,
      "completedPages": "2",
      "completed": true,
      "id": 9
    },
    {
      "title": "123",
      "authorName": "sdsds",
      "authorSurname": "sdsds",
      "pages": 111,
      "completedPages": "2",
      "completed": true,
      "id": 10
    },
    {
      "title": "123",
      "authorName": "sdsds",
      "authorSurname": "sdsds",
      "pages": 111,
      "completedPages": "2",
      "completed": true,
      "id": 11
    },
    {
      "title": "123",
      "authorName": "sdsds",
      "authorSurname": "sdsds",
      "pages": 111,
      "completedPages": "2",
      "completed": true,
      "id": 12
    },
    {
      "title": "123",
      "authorName": "sdsds",
      "authorSurname": "sdsds",
      "pages": 111,
      "completedPages": "2",
      "completed": true,
      "id": 13
    },
    {
      "title": "123",
      "authorName": "sdsds",
      "authorSurname": "sdsds",
      "pages": 111,
      "completedPages": "2",
      "completed": true,
      "id": 14
    },
    {
      "title": "123",
      "authorName": "sdsds",
      "authorSurname": "sdsds",
      "pages": 111,
      "completedPages": "2",
      "completed": true,
      "id": 15
    },
    {
      "title": "123",
      "authorName": "sdsds",
      "authorSurname": "sdsds",
      "pages": 111,
      "completedPages": "2",
      "completed": true,
      "id": 16
    },
    {
      "title": "123",
      "authorName": "sdsds",
      "authorSurname": "sdsds",
      "pages": 111,
      "completedPages": "2",
      "completed": true,
      "id": 17
    },
    {
      "title": "123",
      "authorName": "sdsds",
      "authorSurname": "sdsds",
      "pages": 111,
      "completedPages": "2",
      "completed": true,
      "id": 18
    },
    {
      "title": "123",
      "authorName": "sdsds",
      "authorSurname": "sdsds",
      "pages": 111,
      "completedPages": "2",
      "completed": true,
      "id": 19
    },
    {
      "title": "123",
      "authorName": "sdsds",
      "authorSurname": "sdsds",
      "pages": 111,
      "completedPages": "2",
      "completed": true,
      "id": 20
    },
    {
      "title": "123",
      "authorName": "sdsds",
      "authorSurname": "sdsds",
      "pages": 111,
      "completedPages": "2",
      "completed": true,
      "id": 21
    }
  ]
}